aws_rekognition_parser_pkg/__init__.py
aws_rekognition_parser_pkg/aws_rekognition_parser.py
aws_rekognition_parser-0.0.1.dist-info/LICENSE
aws_rekognition_parser-0.0.1.dist-info/METADATA
aws_rekognition_parser-0.0.1.dist-info/WHEEL
aws_rekognition_parser-0.0.1.dist-info/top_level.txt
aws_rekognition_parser-0.0.1.dist-info/RECORD
