Metadata-Version: 2.1
Name: aws_rekognition_parser
Version: 0.0.1
Summary: AWS Rekognition output parser for receipt text
Home-page: https://github.com/x21120501/aws_rekognition_parser
Author: x21120501
License: UNKNOWN
Platform: UNKNOWN
Classifier: Programming Language :: Python :: 3
Classifier: License :: OSI Approved :: MIT License
Classifier: Operating System :: OS Independent
Requires-Python: >=3.6
License-File: LICENSE
